{"as_of": "2019-07-30T21:07:48Z", "created_at": "2019-07-30T21:00:25Z", "locations": [{"name": "Venezuela", "woeid": 23424982}], "trends": [{"name": "#2A\u00f1osDePazANC", "promoted_content": null, "query": "%232A%C3%B1osDePazANC", "tweet_volume": 161483, "url": "http://twitter.com/search?q=%232A%C3%B1osDePazANC"}, {"name": "#30Jul", "promoted_content": null, "query": "%2330Jul", "tweet_volume": 86152, "url": "http://twitter.com/search?q=%2330Jul"}, {"name": "#DiaInternacionaldelaAmistad", "promoted_content": null, "query": "%23DiaInternacionaldelaAmistad", "tweet_volume": 71902, "url": "http://twitter.com/search?q=%23DiaInternacionaldelaAmistad"}, {"name": "Altagracia de Orituco", "promoted_content": null, "query": "%22Altagracia+de+Orituco%22", "tweet_volume": null, "url": "http://twitter.com/search?q=%22Altagracia+de+Orituco%22"}, {"name": "#citgoala1", "promoted_content": null, "query": "%23citgoala1", "tweet_volume": null, "url": "http://twitter.com/search?q=%23citgoala1"}, {"name": "Marcelo", "promoted_content": null, "query": "Marcelo", "tweet_volume": 62932, "url": "http://twitter.com/search?q=Marcelo"}, {"name": "Lucas V\u00e1zquez", "promoted_content": null, "query": "%22Lucas+V%C3%A1zquez%22", "tweet_volume": 18823, "url": "http://twitter.com/search?q=%22Lucas+V%C3%A1zquez%22"}, {"name": "Gabriela Montero", "promoted_content": null, "query": "%22Gabriela+Montero%22", "tweet_volume": null, "url": "http://twitter.com/search?q=%22Gabriela+Montero%22"}, {"name": "#AudiCup2019", "promoted_content": null, "query": "%23AudiCup2019", "tweet_volume": 45458, "url": "http://twitter.com/search?q=%23AudiCup2019"}, {"name": "Parlamento", "promoted_content": null, "query": "Parlamento", "tweet_volume": 15668, "url": "http://twitter.com/search?q=Parlamento"}, {"name": "Keylor", "promoted_content": null, "query": "Keylor", "tweet_volume": 16601, "url": "http://twitter.com/search?q=Keylor"}, {"name": "Huawei", "promoted_content": null, "query": "Huawei", "tweet_volume": 30723, "url": "http://twitter.com/search?q=Huawei"}, {"name": "Hace 19", "promoted_content": null, "query": "%22Hace+19%22", "tweet_volume": null, "url": "http://twitter.com/search?q=%22Hace+19%22"}, {"name": "constituyente", "promoted_content": null, "query": "constituyente", "tweet_volume": 16460, "url": "http://twitter.com/search?q=constituyente"}, {"name": "Fernando Alb\u00e1n", "promoted_content": null, "query": "%22Fernando+Alb%C3%A1n%22", "tweet_volume": null, "url": "http://twitter.com/search?q=%22Fernando+Alb%C3%A1n%22"}, {"name": "Dark Horse", "promoted_content": null, "query": "%22Dark+Horse%22", "tweet_volume": 48487, "url": "http://twitter.com/search?q=%22Dark+Horse%22"}, {"name": "Embajador de Alemania", "promoted_content": null, "query": "%22Embajador+de+Alemania%22", "tweet_volume": null, "url": "http://twitter.com/search?q=%22Embajador+de+Alemania%22"}, {"name": "Trata de Personas", "promoted_content": null, "query": "%22Trata+de+Personas%22", "tweet_volume": 26706, "url": "http://twitter.com/search?q=%22Trata+de+Personas%22"}, {"name": "Crystallex", "promoted_content": null, "query": "Crystallex", "tweet_volume": null, "url": "http://twitter.com/search?q=Crystallex"}, {"name": "Miguel Cabrera", "promoted_content": null, "query": "%22Miguel+Cabrera%22", "tweet_volume": null, "url": "http://twitter.com/search?q=%22Miguel+Cabrera%22"}, {"name": "VANESSA DAVIES", "promoted_content": null, "query": "%22VANESSA+DAVIES%22", "tweet_volume": null, "url": "http://twitter.com/search?q=%22VANESSA+DAVIES%22"}, {"name": "Cruz Diez", "promoted_content": null, "query": "%22Cruz+Diez%22", "tweet_volume": 19792, "url": "http://twitter.com/search?q=%22Cruz+Diez%22"}, {"name": "Pepe Mujica", "promoted_content": null, "query": "%22Pepe+Mujica%22", "tweet_volume": null, "url": "http://twitter.com/search?q=%22Pepe+Mujica%22"}, {"name": "Keydomar Vallenilla", "promoted_content": null, "query": "%22Keydomar+Vallenilla%22", "tweet_volume": null, "url": "http://twitter.com/search?q=%22Keydomar+Vallenilla%22"}, {"name": "arturo michelena", "promoted_content": null, "query": "%22arturo+michelena%22", "tweet_volume": null, "url": "http://twitter.com/search?q=%22arturo+michelena%22"}, {"name": "samuel sosa", "promoted_content": null, "query": "%22samuel+sosa%22", "tweet_volume": null, "url": "http://twitter.com/search?q=%22samuel+sosa%22"}, {"name": "Torre Eiffel", "promoted_content": null, "query": "%22Torre+Eiffel%22", "tweet_volume": null, "url": "http://twitter.com/search?q=%22Torre+Eiffel%22"}, {"name": "Colombia", "promoted_content": null, "query": "Colombia", "tweet_volume": 132818, "url": "http://twitter.com/search?q=Colombia"}, {"name": "Carmen Victoria P\u00e9rez", "promoted_content": null, "query": "%22Carmen+Victoria+P%C3%A9rez%22", "tweet_volume": null, "url": "http://twitter.com/search?q=%22Carmen+Victoria+P%C3%A9rez%22"}, {"name": "Gustavo Dudamel", "promoted_content": null, "query": "%22Gustavo+Dudamel%22", "tweet_volume": null, "url": "http://twitter.com/search?q=%22Gustavo+Dudamel%22"}, {"name": "Ch\u00e1vez", "promoted_content": null, "query": "Ch%C3%A1vez", "tweet_volume": 83007, "url": "http://twitter.com/search?q=Ch%C3%A1vez"}, {"name": "Gabriela del Mar", "promoted_content": null, "query": "%22Gabriela+del+Mar%22", "tweet_volume": null, "url": "http://twitter.com/search?q=%22Gabriela+del+Mar%22"}, {"name": "cristopher figuera", "promoted_content": null, "query": "%22cristopher+figuera%22", "tweet_volume": null, "url": "http://twitter.com/search?q=%22cristopher+figuera%22"}, {"name": "Espa\u00f1a", "promoted_content": null, "query": "Espa%C3%B1a", "tweet_volume": 210761, "url": "http://twitter.com/search?q=Espa%C3%B1a"}, {"name": "Traki", "promoted_content": null, "query": "Traki", "tweet_volume": null, "url": "http://twitter.com/search?q=Traki"}, {"name": "Palacio Federal Legislativo", "promoted_content": null, "query": "%22Palacio+Federal+Legislativo%22", "tweet_volume": null, "url": "http://twitter.com/search?q=%22Palacio+Federal+Legislativo%22"}, {"name": "Fortnite", "promoted_content": null, "query": "Fortnite", "tweet_volume": 209584, "url": "http://twitter.com/search?q=Fortnite"}, {"name": "#LIBRESYSEGURAS", "promoted_content": null, "query": "%23LIBRESYSEGURAS", "tweet_volume": null, "url": "http://twitter.com/search?q=%23LIBRESYSEGURAS"}, {"name": "#29Jul", "promoted_content": null, "query": "%2329Jul", "tweet_volume": 57066, "url": "http://twitter.com/search?q=%2329Jul"}, {"name": "#FelizMartes", "promoted_content": null, "query": "%23FelizMartes", "tweet_volume": 53982, "url": "http://twitter.com/search?q=%23FelizMartes"}, {"name": "#Uni\u00f3nRevoluci\u00f3nYPaz", "promoted_content": null, "query": "%23Uni%C3%B3nRevoluci%C3%B3nYPaz", "tweet_volume": 181609, "url": "http://twitter.com/search?q=%23Uni%C3%B3nRevoluci%C3%B3nYPaz"}, {"name": "#NoMasChavistasAsesinados", "promoted_content": null, "query": "%23NoMasChavistasAsesinados", "tweet_volume": 19684, "url": "http://twitter.com/search?q=%23NoMasChavistasAsesinados"}, {"name": "#PrimeraPagina", "promoted_content": null, "query": "%23PrimeraPagina", "tweet_volume": null, "url": "http://twitter.com/search?q=%23PrimeraPagina"}, {"name": "#feliziniciodesemana", "promoted_content": null, "query": "%23feliziniciodesemana", "tweet_volume": null, "url": "http://twitter.com/search?q=%23feliziniciodesemana"}, {"name": "#nomasasesinatodechavistas", "promoted_content": null, "query": "%23nomasasesinatodechavistas", "tweet_volume": null, "url": "http://twitter.com/search?q=%23nomasasesinatodechavistas"}, {"name": "#btslovemyself", "promoted_content": null, "query": "%23btslovemyself", "tweet_volume": 1099230, "url": "http://twitter.com/search?q=%23btslovemyself"}, {"name": "#buenosdiasatodos", "promoted_content": null, "query": "%23buenosdiasatodos", "tweet_volume": null, "url": "http://twitter.com/search?q=%23buenosdiasatodos"}, {"name": "#SolidarioEnSintonia", "promoted_content": null, "query": "%23SolidarioEnSintonia", "tweet_volume": null, "url": "http://twitter.com/search?q=%23SolidarioEnSintonia"}, {"name": "#SoyLuna", "promoted_content": null, "query": "%23SoyLuna", "tweet_volume": 254330, "url": "http://twitter.com/search?q=%23SoyLuna"}, {"name": "#rlozinski", "promoted_content": null, "query": "%23rlozinski", "tweet_volume": null, "url": "http://twitter.com/search?q=%23rlozinski"}]}
