{"as_of": "2019-08-03T11:35:32Z", "created_at": "2019-08-03T11:27:56Z", "locations": [{"name": "Worldwide", "woeid": 1}], "trends": [{"name": "#NoMoreDream100M", "promoted_content": null, "query": "%23NoMoreDream100M", "tweet_volume": 47410, "url": "http://twitter.com/search?q=%23NoMoreDream100M"}, {"name": "#sigarayazam", "promoted_content": null, "query": "%23sigarayazam", "tweet_volume": 19188, "url": "http://twitter.com/search?q=%23sigarayazam"}, {"name": "\u82b1\u706b\u306e\u97f3", "promoted_content": null, "query": "%E8%8A%B1%E7%81%AB%E3%81%AE%E9%9F%B3", "tweet_volume": 15014, "url": "http://twitter.com/search?q=%E8%8A%B1%E7%81%AB%E3%81%AE%E9%9F%B3"}, {"name": "#SMTOWNLIVE2019inTOKYO", "promoted_content": null, "query": "%23SMTOWNLIVE2019inTOKYO", "tweet_volume": 118934, "url": "http://twitter.com/search?q=%23SMTOWNLIVE2019inTOKYO"}, {"name": "#\u30b0\u30e9\u30d6\u30eb\u590f\u771f\u3063\u76db\u308a", "promoted_content": null, "query": "%23%E3%82%B0%E3%83%A9%E3%83%96%E3%83%AB%E5%A4%8F%E7%9C%9F%E3%81%A3%E7%9B%9B%E3%82%8A", "tweet_volume": 168656, "url": "http://twitter.com/search?q=%23%E3%82%B0%E3%83%A9%E3%83%96%E3%83%AB%E5%A4%8F%E7%9C%9F%E3%81%A3%E7%9B%9B%E3%82%8A"}, {"name": "#\u4e16\u754c\u4e00\u53d7\u3051\u305f\u3044\u6388\u696d", "promoted_content": null, "query": "%23%E4%B8%96%E7%95%8C%E4%B8%80%E5%8F%97%E3%81%91%E3%81%9F%E3%81%84%E6%8E%88%E6%A5%AD", "tweet_volume": null, "url": "http://twitter.com/search?q=%23%E4%B8%96%E7%95%8C%E4%B8%80%E5%8F%97%E3%81%91%E3%81%9F%E3%81%84%E6%8E%88%E6%A5%AD"}, {"name": "\u30de\u30fc\u30ea\u30f3", "promoted_content": null, "query": "%E3%83%9E%E3%83%BC%E3%83%AA%E3%83%B3", "tweet_volume": 143944, "url": "http://twitter.com/search?q=%E3%83%9E%E3%83%BC%E3%83%AA%E3%83%B3"}, {"name": "\u30de\u30b0\u30ca", "promoted_content": null, "query": "%E3%83%9E%E3%82%B0%E3%83%8A", "tweet_volume": 17076, "url": "http://twitter.com/search?q=%E3%83%9E%E3%82%B0%E3%83%8A"}, {"name": "\u8272\u9055\u3044", "promoted_content": null, "query": "%E8%89%B2%E9%81%95%E3%81%84", "tweet_volume": 30579, "url": "http://twitter.com/search?q=%E8%89%B2%E9%81%95%E3%81%84"}, {"name": "Moeen Ali", "promoted_content": null, "query": "%22Moeen+Ali%22", "tweet_volume": null, "url": "http://twitter.com/search?q=%22Moeen+Ali%22"}, {"name": "\u30e9\u30eb\u30c8\u30b9", "promoted_content": null, "query": "%E3%83%A9%E3%83%AB%E3%83%88%E3%82%B9", "tweet_volume": 34018, "url": "http://twitter.com/search?q=%E3%83%A9%E3%83%AB%E3%83%88%E3%82%B9"}, {"name": "\u795e\u77f3\u6700\u7d42", "promoted_content": null, "query": "%E7%A5%9E%E7%9F%B3%E6%9C%80%E7%B5%82", "tweet_volume": null, "url": "http://twitter.com/search?q=%E7%A5%9E%E7%9F%B3%E6%9C%80%E7%B5%82"}, {"name": "\u30e9\u30ab\u30e0", "promoted_content": null, "query": "%E3%83%A9%E3%82%AB%E3%83%A0", "tweet_volume": 11336, "url": "http://twitter.com/search?q=%E3%83%A9%E3%82%AB%E3%83%A0"}, {"name": "\u6c96\u7530\u3055\u3093", "promoted_content": null, "query": "%E6%B2%96%E7%94%B0%E3%81%95%E3%82%93", "tweet_volume": 65580, "url": "http://twitter.com/search?q=%E6%B2%96%E7%94%B0%E3%81%95%E3%82%93"}, {"name": "\u6b66\u8535\u3061\u3083\u3093", "promoted_content": null, "query": "%E6%AD%A6%E8%94%B5%E3%81%A1%E3%82%83%E3%82%93", "tweet_volume": 55084, "url": "http://twitter.com/search?q=%E6%AD%A6%E8%94%B5%E3%81%A1%E3%82%83%E3%82%93"}, {"name": "\ud53c\ucc98\ub9c1", "promoted_content": null, "query": "%ED%94%BC%EC%B2%98%EB%A7%81", "tweet_volume": 18099, "url": "http://twitter.com/search?q=%ED%94%BC%EC%B2%98%EB%A7%81"}, {"name": "\u795e\u77f34\u51f8", "promoted_content": null, "query": "%E7%A5%9E%E7%9F%B34%E5%87%B8", "tweet_volume": null, "url": "http://twitter.com/search?q=%E7%A5%9E%E7%9F%B34%E5%87%B8"}, {"name": "\u4e16\u754c\u306e\u7247\u9685", "promoted_content": null, "query": "%E4%B8%96%E7%95%8C%E3%81%AE%E7%89%87%E9%9A%85", "tweet_volume": 40301, "url": "http://twitter.com/search?q=%E4%B8%96%E7%95%8C%E3%81%AE%E7%89%87%E9%9A%85"}, {"name": "RPG\u30e2\u30fc\u30c9", "promoted_content": null, "query": "RPG%E3%83%A2%E3%83%BC%E3%83%89", "tweet_volume": null, "url": "http://twitter.com/search?q=RPG%E3%83%A2%E3%83%BC%E3%83%89"}, {"name": "GBVS", "promoted_content": null, "query": "GBVS", "tweet_volume": null, "url": "http://twitter.com/search?q=GBVS"}, {"name": "\uadf8\ub798\ube44\ud2f0", "promoted_content": null, "query": "%EA%B7%B8%EB%9E%98%EB%B9%84%ED%8B%B0", "tweet_volume": 14148, "url": "http://twitter.com/search?q=%EA%B7%B8%EB%9E%98%EB%B9%84%ED%8B%B0"}, {"name": "\u30e9\u30a4\u30b8\u30f3\u30b0\u30d5\u30a9\u30fc\u30b9", "promoted_content": null, "query": "%E3%83%A9%E3%82%A4%E3%82%B8%E3%83%B3%E3%82%B0%E3%83%95%E3%82%A9%E3%83%BC%E3%82%B9", "tweet_volume": null, "url": "http://twitter.com/search?q=%E3%83%A9%E3%82%A4%E3%82%B8%E3%83%B3%E3%82%B0%E3%83%95%E3%82%A9%E3%83%BC%E3%82%B9"}, {"name": "\u8868\u73fe\u306e\u4e0d\u81ea\u7531\u5c55", "promoted_content": null, "query": "%E8%A1%A8%E7%8F%BE%E3%81%AE%E4%B8%8D%E8%87%AA%E7%94%B1%E5%B1%95", "tweet_volume": 126390, "url": "http://twitter.com/search?q=%E8%A1%A8%E7%8F%BE%E3%81%AE%E4%B8%8D%E8%87%AA%E7%94%B1%E5%B1%95"}, {"name": "\u5730\u5143\u306e\u82b1\u706b\u5927\u4f1a", "promoted_content": null, "query": "%E5%9C%B0%E5%85%83%E3%81%AE%E8%8A%B1%E7%81%AB%E5%A4%A7%E4%BC%9A", "tweet_volume": null, "url": "http://twitter.com/search?q=%E5%9C%B0%E5%85%83%E3%81%AE%E8%8A%B1%E7%81%AB%E5%A4%A7%E4%BC%9A"}, {"name": "\u30b3\u30df\u30e5\u30cb\u30c6\u30a3\u30c7\u30a4", "promoted_content": null, "query": "%E3%82%B3%E3%83%9F%E3%83%A5%E3%83%8B%E3%83%86%E3%82%A3%E3%83%87%E3%82%A4", "tweet_volume": null, "url": "http://twitter.com/search?q=%E3%82%B3%E3%83%9F%E3%83%A5%E3%83%8B%E3%83%86%E3%82%A3%E3%83%87%E3%82%A4"}, {"name": "Nineveh", "promoted_content": null, "query": "Nineveh", "tweet_volume": null, "url": "http://twitter.com/search?q=Nineveh"}, {"name": "\ud53c\uccd0\ub9c1", "promoted_content": null, "query": "%ED%94%BC%EC%B3%90%EB%A7%81", "tweet_volume": 17214, "url": "http://twitter.com/search?q=%ED%94%BC%EC%B3%90%EB%A7%81"}, {"name": "\u30ea\u30ea\u30f3\u30af", "promoted_content": null, "query": "%E3%83%AA%E3%83%AA%E3%83%B3%E3%82%AF", "tweet_volume": null, "url": "http://twitter.com/search?q=%E3%83%AA%E3%83%AA%E3%83%B3%E3%82%AF"}, {"name": "#FreeSowore", "promoted_content": null, "query": "%23FreeSowore", "tweet_volume": 32530, "url": "http://twitter.com/search?q=%23FreeSowore"}, {"name": "#\uc81c_\uadf8\ub9bc\uccb4\ub294_\uc5b4\ub514\uc11c_\ud2f0\uac00_\ub098\ub098\uc694", "promoted_content": null, "query": "%23%EC%A0%9C_%EA%B7%B8%EB%A6%BC%EC%B2%B4%EB%8A%94_%EC%96%B4%EB%94%94%EC%84%9C_%ED%8B%B0%EA%B0%80_%EB%82%98%EB%82%98%EC%9A%94", "tweet_volume": null, "url": "http://twitter.com/search?q=%23%EC%A0%9C_%EA%B7%B8%EB%A6%BC%EC%B2%B4%EB%8A%94_%EC%96%B4%EB%94%94%EC%84%9C_%ED%8B%B0%EA%B0%80_%EB%82%98%EB%82%98%EC%9A%94"}, {"name": "#\u0645\u0646\u064a_\u0627\u0631\u062c\u0639\u064a_\u0644\u0645\u062d\u0645\u062f_\u0648\u0644\u062f_\u062e\u0627\u0644\u062a\u0643", "promoted_content": null, "query": "%23%D9%85%D9%86%D9%8A_%D8%A7%D8%B1%D8%AC%D8%B9%D9%8A_%D9%84%D9%85%D8%AD%D9%85%D8%AF_%D9%88%D9%84%D8%AF_%D8%AE%D8%A7%D9%84%D8%AA%D9%83", "tweet_volume": null, "url": "http://twitter.com/search?q=%23%D9%85%D9%86%D9%8A_%D8%A7%D8%B1%D8%AC%D8%B9%D9%8A_%D9%84%D9%85%D8%AD%D9%85%D8%AF_%D9%88%D9%84%D8%AF_%D8%AE%D8%A7%D9%84%D8%AA%D9%83"}, {"name": "#\ub3c4\uacb8\uc544\ub354_\uacc1\uc5d0\uc11c_\ub05d\uae4c\uc9c0_\uc9c0\ud0a4\ub9ac\ub77c", "promoted_content": null, "query": "%23%EB%8F%84%EA%B2%B8%EC%95%84%EB%8D%94_%EA%B3%81%EC%97%90%EC%84%9C_%EB%81%9D%EA%B9%8C%EC%A7%80_%EC%A7%80%ED%82%A4%EB%A6%AC%EB%9D%BC", "tweet_volume": 31428, "url": "http://twitter.com/search?q=%23%EB%8F%84%EA%B2%B8%EC%95%84%EB%8D%94_%EA%B3%81%EC%97%90%EC%84%9C_%EB%81%9D%EA%B9%8C%EC%A7%80_%EC%A7%80%ED%82%A4%EB%A6%AC%EB%9D%BC"}, {"name": "#cumartesi", "promoted_content": null, "query": "%23cumartesi", "tweet_volume": 17506, "url": "http://twitter.com/search?q=%23cumartesi"}, {"name": "#StillWithTreasure13", "promoted_content": null, "query": "%23StillWithTreasure13", "tweet_volume": 30429, "url": "http://twitter.com/search?q=%23StillWithTreasure13"}, {"name": "#GiveawayMcDonalds", "promoted_content": null, "query": "%23GiveawayMcDonalds", "tweet_volume": null, "url": "http://twitter.com/search?q=%23GiveawayMcDonalds"}, {"name": "#\u0627\u0633\u0642\u0627\u0637_\u0627\u0644\u0646\u0641\u0642\u0647_\u0627\u0644\u0645\u0647\u0631_\u0639\u0646_\u0627\u0644\u0633\u0639\u0648\u062f\u064a1", "promoted_content": null, "query": "%23%D8%A7%D8%B3%D9%82%D8%A7%D8%B7_%D8%A7%D9%84%D9%86%D9%81%D9%82%D9%87_%D8%A7%D9%84%D9%85%D9%87%D8%B1_%D8%B9%D9%86_%D8%A7%D9%84%D8%B3%D8%B9%D9%88%D8%AF%D9%8A1", "tweet_volume": null, "url": "http://twitter.com/search?q=%23%D8%A7%D8%B3%D9%82%D8%A7%D8%B7_%D8%A7%D9%84%D9%86%D9%81%D9%82%D9%87_%D8%A7%D9%84%D9%85%D9%87%D8%B1_%D8%B9%D9%86_%D8%A7%D9%84%D8%B3%D8%B9%D9%88%D8%AF%D9%8A1"}, {"name": "#KashmirUnderThreat", "promoted_content": null, "query": "%23KashmirUnderThreat", "tweet_volume": 19623, "url": "http://twitter.com/search?q=%23KashmirUnderThreat"}, {"name": "#wemissyoufx", "promoted_content": null, "query": "%23wemissyoufx", "tweet_volume": 14712, "url": "http://twitter.com/search?q=%23wemissyoufx"}, {"name": "#\u0627\u062d\u0628\u0643_\u0645\u0648\u062a_\u064a\u0627\u0647\u0646\u0627\u062f\u064a", "promoted_content": null, "query": "%23%D8%A7%D8%AD%D8%A8%D9%83_%D9%85%D9%88%D8%AA_%D9%8A%D8%A7%D9%87%D9%86%D8%A7%D8%AF%D9%8A", "tweet_volume": null, "url": "http://twitter.com/search?q=%23%D8%A7%D8%AD%D8%A8%D9%83_%D9%85%D9%88%D8%AA_%D9%8A%D8%A7%D9%87%D9%86%D8%A7%D8%AF%D9%8A"}, {"name": "#PBBCelebr8AtTheBigNight", "promoted_content": null, "query": "%23PBBCelebr8AtTheBigNight", "tweet_volume": 24451, "url": "http://twitter.com/search?q=%23PBBCelebr8AtTheBigNight"}, {"name": "#DADDYSGURLParangNormal", "promoted_content": null, "query": "%23DADDYSGURLParangNormal", "tweet_volume": 33209, "url": "http://twitter.com/search?q=%23DADDYSGURLParangNormal"}, {"name": "#\u30b8\u30e7\u30d6\u30c1\u30e5\u30fc\u30f3", "promoted_content": null, "query": "%23%E3%82%B8%E3%83%A7%E3%83%96%E3%83%81%E3%83%A5%E3%83%BC%E3%83%B3", "tweet_volume": null, "url": "http://twitter.com/search?q=%23%E3%82%B8%E3%83%A7%E3%83%96%E3%83%81%E3%83%A5%E3%83%BC%E3%83%B3"}, {"name": "#C\u00fcneytCebenoyan", "promoted_content": null, "query": "%23C%C3%BCneytCebenoyan", "tweet_volume": null, "url": "http://twitter.com/search?q=%23C%C3%BCneytCebenoyan"}, {"name": "#\u0627\u0643\u062b\u0631_\u0648\u0642\u062a\u064a_\u064a\u0636\u064a\u0639_\u0639\u0644\u064a", "promoted_content": null, "query": "%23%D8%A7%D9%83%D8%AB%D8%B1_%D9%88%D9%82%D8%AA%D9%8A_%D9%8A%D8%B6%D9%8A%D8%B9_%D8%B9%D9%84%D9%8A", "tweet_volume": null, "url": "http://twitter.com/search?q=%23%D8%A7%D9%83%D8%AB%D8%B1_%D9%88%D9%82%D8%AA%D9%8A_%D9%8A%D8%B6%D9%8A%D8%B9_%D8%B9%D9%84%D9%8A"}, {"name": "#kimimachi", "promoted_content": null, "query": "%23kimimachi", "tweet_volume": null, "url": "http://twitter.com/search?q=%23kimimachi"}, {"name": "#AFLDeesTigers", "promoted_content": null, "query": "%23AFLDeesTigers", "tweet_volume": null, "url": "http://twitter.com/search?q=%23AFLDeesTigers"}, {"name": "#HelloLoveGoobye", "promoted_content": null, "query": "%23HelloLoveGoobye", "tweet_volume": 22423, "url": "http://twitter.com/search?q=%23HelloLoveGoobye"}, {"name": "#SaturdayThoughts", "promoted_content": null, "query": "%23SaturdayThoughts", "tweet_volume": 15557, "url": "http://twitter.com/search?q=%23SaturdayThoughts"}, {"name": "#Flamme", "promoted_content": null, "query": "%23Flamme", "tweet_volume": 37328, "url": "http://twitter.com/search?q=%23Flamme"}, {"name": "#FelizSabado", "promoted_content": null, "query": "%23FelizSabado", "tweet_volume": null, "url": "http://twitter.com/search?q=%23FelizSabado"}]}
