{"as_of": "2019-07-30T17:52:04Z", "created_at": "2019-07-30T17:48:10Z", "locations": [{"name": "Colombia", "woeid": 23424787}], "trends": [{"name": "#RespetoALaMujerNoSeNegocia", "promoted_content": null, "query": "%23RespetoALaMujerNoSeNegocia", "tweet_volume": null, "url": "http://twitter.com/search?q=%23RespetoALaMujerNoSeNegocia"}, {"name": "#CruzDeBoyaca", "promoted_content": null, "query": "%23CruzDeBoyaca", "tweet_volume": null, "url": "http://twitter.com/search?q=%23CruzDeBoyaca"}, {"name": "#FelizMartes", "promoted_content": null, "query": "%23FelizMartes", "tweet_volume": 43665, "url": "http://twitter.com/search?q=%23FelizMartes"}, {"name": "#IdeasQueConstruyen", "promoted_content": null, "query": "%23IdeasQueConstruyen", "tweet_volume": null, "url": "http://twitter.com/search?q=%23IdeasQueConstruyen"}, {"name": "#NoM\u00e1sTesteoAnimal", "promoted_content": null, "query": "%23NoM%C3%A1sTesteoAnimal", "tweet_volume": null, "url": "http://twitter.com/search?q=%23NoM%C3%A1sTesteoAnimal"}, {"name": "Lucas V\u00e1zquez", "promoted_content": null, "query": "%22Lucas+V%C3%A1zquez%22", "tweet_volume": null, "url": "http://twitter.com/search?q=%22Lucas+V%C3%A1zquez%22"}, {"name": "The Economist", "promoted_content": null, "query": "%22The+Economist%22", "tweet_volume": null, "url": "http://twitter.com/search?q=%22The+Economist%22"}, {"name": "Keylor", "promoted_content": null, "query": "Keylor", "tweet_volume": null, "url": "http://twitter.com/search?q=Keylor"}, {"name": "santiago giraldo", "promoted_content": null, "query": "%22santiago+giraldo%22", "tweet_volume": null, "url": "http://twitter.com/search?q=%22santiago+giraldo%22"}, {"name": "Benzema", "promoted_content": null, "query": "Benzema", "tweet_volume": null, "url": "http://twitter.com/search?q=Benzema"}, {"name": "Puente de Boyac\u00e1", "promoted_content": null, "query": "%22Puente+de+Boyac%C3%A1%22", "tweet_volume": null, "url": "http://twitter.com/search?q=%22Puente+de+Boyac%C3%A1%22"}, {"name": "Colpensiones", "promoted_content": null, "query": "Colpensiones", "tweet_volume": null, "url": "http://twitter.com/search?q=Colpensiones"}, {"name": "Mariano", "promoted_content": null, "query": "Mariano", "tweet_volume": 16254, "url": "http://twitter.com/search?q=Mariano"}, {"name": "Bayer", "promoted_content": null, "query": "Bayer", "tweet_volume": null, "url": "http://twitter.com/search?q=Bayer"}, {"name": "Hoy 30", "promoted_content": null, "query": "%22Hoy+30%22", "tweet_volume": null, "url": "http://twitter.com/search?q=%22Hoy+30%22"}, {"name": "El Bosque", "promoted_content": null, "query": "%22El+Bosque%22", "tweet_volume": null, "url": "http://twitter.com/search?q=%22El+Bosque%22"}, {"name": "Improductivo", "promoted_content": null, "query": "Improductivo", "tweet_volume": null, "url": "http://twitter.com/search?q=Improductivo"}, {"name": "Iv\u00e1n Mej\u00eda", "promoted_content": null, "query": "%22Iv%C3%A1n+Mej%C3%ADa%22", "tweet_volume": null, "url": "http://twitter.com/search?q=%22Iv%C3%A1n+Mej%C3%ADa%22"}, {"name": "Orden al M\u00e9rito", "promoted_content": null, "query": "%22Orden+al+M%C3%A9rito%22", "tweet_volume": null, "url": "http://twitter.com/search?q=%22Orden+al+M%C3%A9rito%22"}, {"name": "Morris", "promoted_content": null, "query": "Morris", "tweet_volume": 28770, "url": "http://twitter.com/search?q=Morris"}, {"name": "China", "promoted_content": null, "query": "China", "tweet_volume": 311028, "url": "http://twitter.com/search?q=China"}, {"name": "Jorge C\u00e1rdenas", "promoted_content": null, "query": "%22Jorge+C%C3%A1rdenas%22", "tweet_volume": null, "url": "http://twitter.com/search?q=%22Jorge+C%C3%A1rdenas%22"}, {"name": "Hollman", "promoted_content": null, "query": "Hollman", "tweet_volume": 14117, "url": "http://twitter.com/search?q=Hollman"}, {"name": "#audicup", "promoted_content": null, "query": "%23audicup", "tweet_volume": 12717, "url": "http://twitter.com/search?q=%23audicup"}, {"name": "#AngelaMar\u00edaEnLaW", "promoted_content": null, "query": "%23AngelaMar%C3%ADaEnLaW", "tweet_volume": null, "url": "http://twitter.com/search?q=%23AngelaMar%C3%ADaEnLaW"}, {"name": "#TrataDePersonas", "promoted_content": null, "query": "%23TrataDePersonas", "tweet_volume": null, "url": "http://twitter.com/search?q=%23TrataDePersonas"}, {"name": "#lasaludencolombia", "promoted_content": null, "query": "%23lasaludencolombia", "tweet_volume": null, "url": "http://twitter.com/search?q=%23lasaludencolombia"}, {"name": "#MasBurroQue", "promoted_content": null, "query": "%23MasBurroQue", "tweet_volume": null, "url": "http://twitter.com/search?q=%23MasBurroQue"}, {"name": "#Dia29DeLlamadoALaCSJ", "promoted_content": null, "query": "%23Dia29DeLlamadoALaCSJ", "tweet_volume": null, "url": "http://twitter.com/search?q=%23Dia29DeLlamadoALaCSJ"}, {"name": "#DiaInternacionaldelaAmistad", "promoted_content": null, "query": "%23DiaInternacionaldelaAmistad", "tweet_volume": 61228, "url": "http://twitter.com/search?q=%23DiaInternacionaldelaAmistad"}, {"name": "#Bogot\u00e1SinTrata", "promoted_content": null, "query": "%23Bogot%C3%A1SinTrata", "tweet_volume": null, "url": "http://twitter.com/search?q=%23Bogot%C3%A1SinTrata"}, {"name": "#D\u00edaNacionalDeLaVidaSilvestre", "promoted_content": null, "query": "%23D%C3%ADaNacionalDeLaVidaSilvestre", "tweet_volume": null, "url": "http://twitter.com/search?q=%23D%C3%ADaNacionalDeLaVidaSilvestre"}, {"name": "#programaci\u00f3nparani\u00f1osyni\u00f1as", "promoted_content": null, "query": "%23programaci%C3%B3nparani%C3%B1osyni%C3%B1as", "tweet_volume": null, "url": "http://twitter.com/search?q=%23programaci%C3%B3nparani%C3%B1osyni%C3%B1as"}, {"name": "#DiaMundialContraLaTrata", "promoted_content": null, "query": "%23DiaMundialContraLaTrata", "tweet_volume": 15256, "url": "http://twitter.com/search?q=%23DiaMundialContraLaTrata"}, {"name": "#PorMiCiudadVoto", "promoted_content": null, "query": "%23PorMiCiudadVoto", "tweet_volume": null, "url": "http://twitter.com/search?q=%23PorMiCiudadVoto"}, {"name": "#Zidane", "promoted_content": null, "query": "%23Zidane", "tweet_volume": null, "url": "http://twitter.com/search?q=%23Zidane"}, {"name": "#CreceConGoogle", "promoted_content": null, "query": "%23CreceConGoogle", "tweet_volume": null, "url": "http://twitter.com/search?q=%23CreceConGoogle"}, {"name": "#NoEsElCosto", "promoted_content": null, "query": "%23NoEsElCosto", "tweet_volume": null, "url": "http://twitter.com/search?q=%23NoEsElCosto"}, {"name": "#YoRechazo", "promoted_content": null, "query": "%23YoRechazo", "tweet_volume": null, "url": "http://twitter.com/search?q=%23YoRechazo"}, {"name": "#30Jul", "promoted_content": null, "query": "%2330Jul", "tweet_volume": 58307, "url": "http://twitter.com/search?q=%2330Jul"}, {"name": "#talentodigital", "promoted_content": null, "query": "%23talentodigital", "tweet_volume": null, "url": "http://twitter.com/search?q=%23talentodigital"}, {"name": "#VivoElFutbolConCafam", "promoted_content": null, "query": "%23VivoElFutbolConCafam", "tweet_volume": null, "url": "http://twitter.com/search?q=%23VivoElFutbolConCafam"}, {"name": "#FelizLunes", "promoted_content": null, "query": "%23FelizLunes", "tweet_volume": 31874, "url": "http://twitter.com/search?q=%23FelizLunes"}, {"name": "#UmbroNoDioLaTalla", "promoted_content": null, "query": "%23UmbroNoDioLaTalla", "tweet_volume": null, "url": "http://twitter.com/search?q=%23UmbroNoDioLaTalla"}, {"name": "#EndViolence", "promoted_content": null, "query": "%23EndViolence", "tweet_volume": 1262883, "url": "http://twitter.com/search?q=%23EndViolence"}, {"name": "#lateleletal", "promoted_content": null, "query": "%23lateleletal", "tweet_volume": null, "url": "http://twitter.com/search?q=%23lateleletal"}, {"name": "#graciasegan", "promoted_content": null, "query": "%23graciasegan", "tweet_volume": null, "url": "http://twitter.com/search?q=%23graciasegan"}, {"name": "#DesafioSuperRegiones", "promoted_content": null, "query": "%23DesafioSuperRegiones", "tweet_volume": null, "url": "http://twitter.com/search?q=%23DesafioSuperRegiones"}, {"name": "#EganBernalCampeon", "promoted_content": null, "query": "%23EganBernalCampeon", "tweet_volume": null, "url": "http://twitter.com/search?q=%23EganBernalCampeon"}, {"name": "#ConstruirPa\u00edsEs", "promoted_content": null, "query": "%23ConstruirPa%C3%ADsEs", "tweet_volume": null, "url": "http://twitter.com/search?q=%23ConstruirPa%C3%ADsEs"}]}
